README.rst
setup.py
pypicgo_tinypng_plugin/__init__.py
pypicgo_tinypng_plugin.egg-info/PKG-INFO
pypicgo_tinypng_plugin.egg-info/SOURCES.txt
pypicgo_tinypng_plugin.egg-info/dependency_links.txt
pypicgo_tinypng_plugin.egg-info/requires.txt
pypicgo_tinypng_plugin.egg-info/top_level.txt